pytoolbelt/toolkit/clitools.py
pytoolbelt/toolkit/config.py
pytoolbelt/toolkit/version.py
pytoolbelt_toolkit-0.4.0.dist-info/METADATA
pytoolbelt_toolkit-0.4.0.dist-info/WHEEL
pytoolbelt_toolkit-0.4.0.dist-info/top_level.txt
pytoolbelt_toolkit-0.4.0.dist-info/RECORD
