Metadata-Version: 2.1
Name: pytoolbelt-toolkit
Version: 0.4.0
Requires-Python: >=3.10
Requires-Dist: pyyaml <7,>=5.3
Provides-Extra: dev
Requires-Dist: setuptools ==68.1.0 ; extra == 'dev'
Requires-Dist: build ==0.10.0 ; extra == 'dev'
Requires-Dist: python-semantic-release ==8.0.6 ; extra == 'dev'
Requires-Dist: pytest ==7.4.0 ; extra == 'dev'
Requires-Dist: black ==23.7.0 ; extra == 'dev'
Requires-Dist: isort ==5.12.0 ; extra == 'dev'
Provides-Extra: docs
Requires-Dist: mkdocs ==1.5.2 ; extra == 'docs'
Requires-Dist: mkdocstrings[python] ==0.22.0 ; extra == 'docs'
Requires-Dist: mkdocs-material ==9.1.21 ; extra == 'docs'
Requires-Dist: markdown-include ==0.8.1 ; extra == 'docs'
